math_lib/__init__.py
math_lib/area.py
math_lib/version.py
tests/__init__.py
tests/test_area.py
math_lib_geometry_maksim_skdm-0.1.0.dist-info/METADATA
math_lib_geometry_maksim_skdm-0.1.0.dist-info/WHEEL
math_lib_geometry_maksim_skdm-0.1.0.dist-info/top_level.txt
math_lib_geometry_maksim_skdm-0.1.0.dist-info/RECORD
