Metadata-Version: 2.4
Name: math-lib-geometry-maksim-skdm
Version: 0.1.0
Author-email: Maksim <maksimgubenin@mail.ru>
Requires-Python: >=3.7
Requires-Dist: setuptools<81.0.0,>=80.9.0
Dynamic: requires-python
